localizablestrings.py
localizablestrings-1.2.dist-info/LICENSE
localizablestrings-1.2.dist-info/METADATA
localizablestrings-1.2.dist-info/WHEEL
localizablestrings-1.2.dist-info/top_level.txt
localizablestrings-1.2.dist-info/RECORD
