Metadata-Version: 2.1
Name: localizablestrings
Version: 1.2
Summary: Localizable.strings reader and writer
Home-page: https://github.com/afoo/localizablestrings
Author: Jan Hülsbergen
Author-email: jan@afoo.de
License: UNKNOWN
Platform: UNKNOWN
Classifier: Programming Language :: Python :: 3
Classifier: License :: OSI Approved :: BSD License
